{
  "name": "TrustChainNetwork",
  "version": "1.0.0",
  "client": {
    "organization": "LTO",
    "connection": {
      "timeout": {
        "peer": {
          "endorser": "300"
        },
        "orderer": "300"
      }
    }
  },
  "organizations": {
    "LTO": {
      "mspid": "LTOMSP",
      "peers": [
        "peer0.lto.gov.ph"
      ],
      "certificateAuthorities": [
        "ca-lto"
      ]
    },
    "HPG": {
      "mspid": "HPGMSP",
      "peers": [
        "peer0.hpg.gov.ph"
      ],
      "certificateAuthorities": [
        "ca-hpg"
      ]
    },
    "Insurance": {
      "mspid": "InsuranceMSP",
      "peers": [
        "peer0.insurance.gov.ph"
      ],
      "certificateAuthorities": [
        "ca-insurance"
      ]
    }
  },
  "peers": {
    "peer0.lto.gov.ph": {
      "url": "grpcs://peer0.lto.gov.ph:7051",
      "grpcOptions": {
        "ssl-target-name-override": "peer0.lto.gov.ph",
        "grpc.keepalive_time_ms": 600000
      },
      "tlsCACerts": {
        "path": "fabric-network/crypto-config/peerOrganizations/lto.gov.ph/peers/peer0.lto.gov.ph/tls/ca.crt"
      }
    },
    "peer0.hpg.gov.ph": {
      "url": "grpcs://peer0.hpg.gov.ph:8051",
      "grpcOptions": {
        "ssl-target-name-override": "peer0.hpg.gov.ph",
        "grpc.keepalive_time_ms": 600000
      },
      "tlsCACerts": {
        "path": "fabric-network/crypto-config/peerOrganizations/hpg.gov.ph/peers/peer0.hpg.gov.ph/tls/ca.crt"
      }
    },
    "peer0.insurance.gov.ph": {
      "url": "grpcs://peer0.insurance.gov.ph:9051",
      "grpcOptions": {
        "ssl-target-name-override": "peer0.insurance.gov.ph",
        "grpc.keepalive_time_ms": 600000
      },
      "tlsCACerts": {
        "path": "fabric-network/crypto-config/peerOrganizations/insurance.gov.ph/peers/peer0.insurance.gov.ph/tls/ca.crt"
      }
    }
  },
  "orderers": {
    "orderer.lto.gov.ph": {
      "url": "grpcs://orderer.lto.gov.ph:7050",
      "grpcOptions": {
        "ssl-target-name-override": "orderer.lto.gov.ph",
        "grpc.keepalive_time_ms": 600000
      },
      "tlsCACerts": {
        "path": "fabric-network/crypto-config/ordererOrganizations/lto.gov.ph/orderers/orderer.lto.gov.ph/tls/ca.crt"
      }
    }
  },
  "channels": {
    "ltochannel": {
      "orderers": [
        "orderer.lto.gov.ph"
      ],
      "peers": {
        "peer0.lto.gov.ph": {
          "endorsingPeer": true,
          "chaincodeQuery": true,
          "ledgerQuery": true,
          "eventSource": true
        },
        "peer0.hpg.gov.ph": {
          "endorsingPeer": true,
          "chaincodeQuery": true,
          "ledgerQuery": true,
          "eventSource": true
        },
        "peer0.insurance.gov.ph": {
          "endorsingPeer": true,
          "chaincodeQuery": true,
          "ledgerQuery": true,
          "eventSource": true
        }
      }
    }
  },
  "certificateAuthorities": {
    "ca-lto": {
      "url": "https://ca-lto:7054",
      "caName": "ca-lto",
      "tlsCACerts": {
        "path": "fabric-network/crypto-config/peerOrganizations/lto.gov.ph/ca/ca.lto.gov.ph-cert.pem"
      }
    },
    "ca-hpg": {
      "url": "https://ca-hpg:8054",
      "caName": "ca-hpg",
      "tlsCACerts": {
        "path": "fabric-network/crypto-config/peerOrganizations/hpg.gov.ph/ca/ca.hpg.gov.ph-cert.pem"
      }
    },
    "ca-insurance": {
      "url": "https://ca-insurance:9054",
      "caName": "ca-insurance",
      "tlsCACerts": {
        "path": "fabric-network/crypto-config/peerOrganizations/insurance.gov.ph/ca/ca.insurance.gov.ph-cert.pem"
      }
    }
  }
}